fetch_paros_data/__init__.py
fetch_paros_data/backup_init.py
fetch_paros_data-0.1.2.dist-info/METADATA
fetch_paros_data-0.1.2.dist-info/WHEEL
fetch_paros_data-0.1.2.dist-info/top_level.txt
fetch_paros_data-0.1.2.dist-info/RECORD
