Metadata-Version: 2.4
Name: fetch-paros-data
Version: 0.1.2
Summary: Fetch and process InfluxDB data from PAROS sensors
Author: Ethan Gelfand
Author-email: Ethan Gelfand <you@example.com>
License: MIT
Requires-Python: >=3.7
Requires-Dist: influxdb-client
Requires-Dist: pandas
Requires-Dist: scipy
Requires-Dist: pytz
Dynamic: author
Dynamic: requires-python
